push_admin/__init__.py
push_admin/_app.py
push_admin/_http.py
push_admin/_message_serializer.py
push_admin/_messages.py
push_admin/messaging.py
python_huawei_push_admin-1.0.0.dist-info/LICENSE
python_huawei_push_admin-1.0.0.dist-info/METADATA
python_huawei_push_admin-1.0.0.dist-info/WHEEL
python_huawei_push_admin-1.0.0.dist-info/top_level.txt
python_huawei_push_admin-1.0.0.dist-info/RECORD
