Metadata-Version: 2.1
Name: python-huawei-push-admin
Version: 1.0.0
Summary: The Huawei Admin Python SDK enables server-side (backend) Python developers to integrate Huawei into their services and applications.
Home-page: https://github.com/TralahM/python_huawei_push_admin
Author: Tralah M Brian
Author-email: briantralah@gmail.com
License: APACHE
Project-URL: Source, https://github.com/TralahM/python_huawei_push_admin
Project-URL: Tracker, https://github.com/TralahM/python_huawei_push_admin/issues
Project-URL: Documentation, https://github.com/TralahM/python_huawei_push_admin
Classifier: Environment :: Web Environment
Classifier: Intended Audience :: Developers
Classifier: License :: OSI Approved :: GNU General Public License v3 (GPLv3)
Classifier: Operating System :: OS Independent
Classifier: Programming Language :: Python
Classifier: Programming Language :: Python :: 3
Classifier: Programming Language :: Python :: 3 :: Only
Classifier: Programming Language :: Python :: 3.6
Classifier: Programming Language :: Python :: 3.7
Classifier: Programming Language :: Python :: 3.8
Classifier: Topic :: Internet :: WWW/HTTP
Classifier: Topic :: Internet :: WWW/HTTP :: Dynamic Content
License-File: LICENSE
Requires-Dist: requests
Provides-Extra: docs
Requires-Dist: sphinx ; extra == 'docs'
Requires-Dist: sphinx-automodapi ; extra == 'docs'
